{"openapi":"3.0.0","paths":{"\/admin\/telegram\/bots":{"get":{"tags":["机器人管理"],"summary":"分页查询机器人","operationId":"fe27829a56673155fc6946eea9e00b9e","parameters":[{"name":"limit","in":"query","description":"每页数量，默认15","required":false,"schema":{"type":"integer"},"rules":null,"attribute":null},{"name":"page","in":"query","description":"页码，默认1","required":false,"schema":{"type":"integer"},"rules":null,"attribute":null},{"name":"keywords","in":"query","description":"关键词查询","required":false,"schema":{"type":"string"},"rules":null,"attribute":null}],"responses":{"200":{"description":"返回值的描述","content":{"application\/json":{"schema":{"properties":{"code":{"description":"code","type":"integer","rules":null,"attribute":null},"data":{"description":"data","type":"array","items":{"$ref":"#\/components\/schemas\/Bot"},"rules":null,"attribute":null}},"type":"object"}}}}}},"post":{"tags":["机器人管理"],"summary":"添加机器人接口","operationId":"9b9ee9f0a3e52539487a34541d8d2afa","requestBody":{"description":"请求参数","content":{"application\/json":{"schema":{"required":["token"],"properties":{"token":{"description":"token","type":"string","rules":null,"attribute":null},"username":{"description":"用户名","type":"string","rules":null,"attribute":null},"nickname":{"description":"昵称","type":"string","rules":null,"attribute":null},"language":{"description":"默认语言","type":"string","rules":null,"attribute":null}},"type":"object"}}},"_content":[{"mediaType":"application\/json","schema":{"required":["token"],"properties":{"token":{"description":"token","type":"string","rules":null,"attribute":null},"username":{"description":"用户名","type":"string","rules":null,"attribute":null},"nickname":{"description":"昵称","type":"string","rules":null,"attribute":null},"language":{"description":"默认语言","type":"string","rules":null,"attribute":null}},"type":"object"}}]},"responses":{"200":{"description":"返回值的描述","content":{"application\/json":{"schema":{"properties":{"code":{"description":"code","type":"integer","rules":null,"attribute":null},"data":{"$ref":"#\/components\/schemas\/Bot"}},"type":"object"}}}}}}},"\/admin\/telegram\/bots\/{id}":{"put":{"tags":["机器人管理"],"summary":"修改机器人接口","operationId":"d114d2ce33d228c83c709c1c3d062dcc","requestBody":{"description":"请求参数","content":{"application\/json":{"schema":{"$ref":"#\/components\/schemas\/Bot"}}},"_content":[{"mediaType":"application\/json","schema":{"$ref":"#\/components\/schemas\/Bot"}}]},"responses":{"200":{"description":"返回值的描述","content":{"application\/json":{"schema":{"properties":{"code":{"description":"code","type":"integer","rules":null,"attribute":null},"data":{"$ref":"#\/components\/schemas\/Bot"}},"type":"object"}}}}}}}},"components":{"schemas":{"Bot":{"description":"机器人信息","properties":{"id":{"description":"id","type":"integer","example":1,"rules":null,"attribute":null},"token":{"description":"token","type":"string","example":"12312312:asdjkhsdfgoidsf","rules":null,"attribute":null},"username":{"description":"用户名","type":"string","example":"my_bot","nullable":true,"rules":null,"attribute":null},"nickname":{"description":"昵称","type":"string","example":"测试机器人","nullable":true,"rules":null,"attribute":null},"language":{"description":"语言(默认 zh_CN 简体中文)","type":"string","example":"zh_CN","rules":null,"attribute":null},"expired_time":{"description":"过期时长（秒）","type":"integer","example":3600,"nullable":true,"rules":null,"attribute":null},"expired_at":{"description":"过期时间","type":"string","format":"date-time","example":"2025-09-11T10:00:00+08:00","nullable":true,"rules":null,"attribute":null},"admins":{"description":"管理员列表","type":"string","example":"123456,654321","nullable":true,"rules":null,"attribute":null},"status":{"description":"状态","type":"string","example":"active","rules":null,"attribute":null}},"type":"object"}}},"servers":[{"url":"http:\/\/127.0.0.1:9501","description":"Test Server"}],"info":{"title":"Sample API","description":"This is a sample API using OpenAPI 3.0 specification","version":"1.0.0"}}